{"transition": {"tecnotree-dclm": {"provenance": {}, "description": "Telco Customer Dataset", "version": "v0.00", "status": "discovery", "connectors": {"pm_transition_tecnotree-dclm": {"raw_uri": "/Users/lkrishna/git/cortex-fabric-examples/notebooks/telco-churn-v2/hadron/meta/tecnotree-dclm/contracts/hadron_pm_transition_tecnotree-dclm.json", "raw_module_name": "ds_discovery.handlers.pandas_handlers", "raw_handler": "PandasPersistHandler", "raw_version": "v0.00", "raw_kwargs": {}, "aligned": false}, "template_source": {"raw_uri": "/Users/lkrishna/git/cortex-fabric-examples/notebooks/telco-churn-v2/hadron/meta/tecnotree-dclm/data", "raw_module_name": "ds_discovery.handlers.pandas_handlers", "raw_handler": "PandasSourceHandler", "raw_version": "v0.00", "raw_kwargs": {}, "aligned": false}, "template_persist": {"raw_uri": "/Users/lkrishna/git/cortex-fabric-examples/notebooks/telco-churn-v2/hadron/meta/tecnotree-dclm/data", "raw_module_name": "ds_discovery.handlers.pandas_handlers", "raw_handler": "PandasPersistHandler", "raw_version": "v0.00", "raw_kwargs": {}, "aligned": false}, "primary_source": {"raw_uri": "s3://lk-datasets/telco/dclm_int_customer_data-20230117-204811.csv", "raw_module_name": "ds_discovery.handlers.s3_handlers", "raw_handler": "S3PersistHandler", "raw_version": "v0.00", "raw_kwargs": {}, "aligned": false}, "primary_persist": {"raw_uri": "/Users/lkrishna/git/cortex-fabric-examples/notebooks/telco-churn-v2/hadron/meta/tecnotree-dclm/data/Telco-Customerselect.parquet", "raw_module_name": "ds_discovery.handlers.pandas_handlers", "raw_handler": "PandasPersistHandler", "raw_version": "v0.00", "raw_kwargs": {}, "aligned": true}}, "intent": {}, "snapshot": {}, "run_book": {}, "meta": {"module": ["ds_discovery", "managers", "transition_property_manager"], "class": "TransitionPropertyManager"}, "knowledge": {"observations": {}, "actions": {}, "attributes": {}, "intent": {}, "schema": {}}}}, "config_meta": {"uid": "81f9d2a2-cc69-4b71-884b-5bd3ed55da54", "create": "2023-01-24 12:20:06.944555", "modify": "2023-01-24 12:21:00.495914", "release": "2.12.34"}}